bulkmailer
