Metadata-Version: 1.0
Name: bulkmailer
Version: 13.6.6
Summary: API library for accessing GAE Bulk Mailer
Home-page: https://github.com/pizzapanther/Bulk-Mailer
Author: Paul Bailey
Author-email: paul.m.bailey@gmail.com
License: BSD
Platform: UNKNOWN
